[
    {
        "file": "blocktypes/stone/drystone.json",
        "op": "remove",
        "path": "/textures",
        "side": "server"

    },
    {
        "file": "blocktypes/stone/drystone.json",
        "op": "add",
        "path": "/texturesbytype",
        "side": "server",
        "value": {
            "@.*-(chalk)": {
                "all": {
                    "base": "block/stone/drystone/{rock}/1",
                    "tiles": [
                        { "base": "block/stone/drystone/{rock}/*" }
                    ],
                    "tilesWidth": 3
                }
            },
            "*-slate": {
                "sides": {
                    "base": "block/stone/drystone/{rock}/sides/1",
                    "tiles": [
                        { "base": "block/stone/drystone/{rock}/sides/*" }
                    ],
                    "tilesWidth": 2
                },
                "up": {
                    "base": "block/stone/drystone/{rock}/top/1",
                    "tiles": [
                        { "base": "block/stone/drystone/{rock}/top/*" }
                    ],
                    "tilesWidth": 2
                },
                "down": {
                    "base": "block/stone/drystone/{rock}/top/1",
                    "tiles": [
                        { "base": "block/stone/drystone/{rock}/top/*" }
                    ],
                    "tilesWidth": 2
                }
            },
            "@.*-(whitemarble|greenmarble)": {
                "all": {
                    "base": "block/stone/drystone/{rock}/*"
                }
            },
            "*": {
                "all": {
                    "base": "block/stone/drystone/{rock}/1",
                    "tiles": [
                        { "base": "block/stone/drystone/{rock}/*" }
                    ],
                    "tilesWidth": 4
                }
            }
        }
    }
]