[

    {
        "file": "blocktypes/stone/cobble/cobblestone.json",
        "op": "remove",
        "path": "/textures",
        "side": "server"
    },
    {
        "file": "blocktypes/stone/cobble/cobblestone.json",
        "op": "add",
        "path": "/texturesbytype",
        "side": "server",
        "value": {
            "@.*-(andesite|kimberlite)": {
                "all": {
                    "base": "block/stone/cobblestone/{rock}/1",
                    "tiles": [
                        { "base": "block/stone/cobblestone/{rock}/*" }
                    ],
                    "tilesWidth": 5
                }
            },
            "*-shale": {
                "all": {
                    "base": "block/stone/cobblestone/{rock}/1",
                    "tiles": [
                        { "base": "block/stone/cobblestone/{rock}/*" }
                    ],
                    "tilesWidth": 3
                }
            },
            "*-slate": {
                "sides": {
                    "base": "block/stone/cobblestone/{rock}/sides/1",
                    "tiles": [
                        { "base": "block/stone/cobblestone/{rock}/sides/*" }
                    ],
                    "tilesWidth": 2
                },
                "up": {
                    "base": "block/stone/cobblestone/{rock}/top/1",
                    "tiles": [
                        { "base": "block/stone/cobblestone/{rock}/top/*" }
                    ],
                    "tilesWidth": 2
                },
                "down": {
                    "base": "block/stone/cobblestone/{rock}/top/1",
                    "tiles": [
                        { "base": "block/stone/cobblestone/{rock}/top/*" }
                    ],
                    "tilesWidth": 2
                }
            },
            "*-limestone": {
                "sides": {
                    "base": "block/stone/cobblestone/{rock}/sides/1",
                    "tiles": [
                        { "base": "block/stone/cobblestone/{rock}/sides/*" }
                    ],
                    "tilesWidth": 5
                },
                "up": {
                    "base": "block/stone/cobblestone/{rock}/top/1",
                    "tiles": [
                        { "base": "block/stone/cobblestone/{rock}/top/*" }
                    ],
                    "tilesWidth": 5
                },
                "down": {
                    "base": "block/stone/cobblestone/{rock}/top/1",
                    "tiles": [
                        { "base": "block/stone/cobblestone/{rock}/top/*" }
                    ],
                    "tilesWidth": 5
                }
            },
            "@.*-(whitemarble|greenmarble|sandstone)": {
                "all": {
                    "base": "block/stone/cobblestone/{rock}/*"
                }
            },
            "*": {
                "all": {
                    "base": "block/stone/cobblestone/{rock}/1",
                    "tiles": [
                        { "base": "block/stone/cobblestone/{rock}/*" }
                    ],
                    "tilesWidth": 4
                }
            }

        }
    }
]
