[

    {
        "file": "conquest:patches/survival/blocktypes/stone/cobble/cobbleslab.json",
        "op": "replace",
        "path": "/1/value",
        "side": "server",
        "dependsOn": [
            {
                "modid": "mngeology"
            }
        ],
        "value": {
            "@.*-(limestone|slate)-.*": {
                "sides": { "base": "game:block/stone/cobblestone/{rock}/sides/*" }
            },
            "@.*-(komatiite|arenite|arkose|marl|travertine|wacke|serpentinite|monzonite|syenite|pyroxenite)-.*": {
                "horizontals": { "base": "game:block/stone/cobblestonestairs/{rock}" },
                "verticals": { "base": "game:block/stone/cobblestone/{rock}1" }
            },
            "*": {
                "sides": { "base": "game:block/stone/cobblestone/{rock}/*" }
            }

        }
    }
]